mcp_cpp_debugger/__init__.py
mcp_cpp_debugger/debugger/__init__.py
mcp_cpp_debugger/debugger/cdb.py
mcp_cpp_debugger/debugger/utils.py
mcp_cpp_debugger/mcp/server.py
mcp_cpp_debugger/utils/log_utils.py
mcp_cpp_debugger-0.1.2.dist-info/METADATA
mcp_cpp_debugger-0.1.2.dist-info/WHEEL
mcp_cpp_debugger-0.1.2.dist-info/entry_points.txt
mcp_cpp_debugger-0.1.2.dist-info/top_level.txt
mcp_cpp_debugger-0.1.2.dist-info/RECORD
