Metadata-Version: 2.4
Name: mcp-cpp-debugger
Version: 0.1.2
Summary: MCP server for C++ debugging, supporting launch, attach, dump analysis, and interactive debugging operations
Author-email: Shanwei <cleardl@qq.com>
Keywords: mcp,debugger,C++,CDB
Requires-Python: >=3.12
Requires-Dist: fastmcp>=2.11.3
